LICENSE
MANIFEST.in
README.rst
setup.py
btc_weasy_pdf.egg-info/PKG-INFO
btc_weasy_pdf.egg-info/SOURCES.txt
btc_weasy_pdf.egg-info/dependency_links.txt
btc_weasy_pdf.egg-info/requires.txt
btc_weasy_pdf.egg-info/top_level.txt
weasy_pdf/__init__.py
weasy_pdf/apps.py
weasy_pdf/views.py
weasy_pdf/static/weasy_pdf/css/helvetica_neue_cyr.css
weasy_pdf/static/weasy_pdf/fonts/Calibri/Calibri.ttf
weasy_pdf/static/weasy_pdf/fonts/HelveticaNeueCyr/HelveticaNeueCyr-Black.eot
weasy_pdf/static/weasy_pdf/fonts/HelveticaNeueCyr/HelveticaNeueCyr-Black.ttf
weasy_pdf/static/weasy_pdf/fonts/HelveticaNeueCyr/HelveticaNeueCyr-Black.woff
weasy_pdf/static/weasy_pdf/fonts/HelveticaNeueCyr/HelveticaNeueCyr-BlackItalic.eot
weasy_pdf/static/weasy_pdf/fonts/HelveticaNeueCyr/HelveticaNeueCyr-BlackItalic.ttf
weasy_pdf/static/weasy_pdf/fonts/HelveticaNeueCyr/HelveticaNeueCyr-BlackItalic.woff
weasy_pdf/static/weasy_pdf/fonts/HelveticaNeueCyr/HelveticaNeueCyr-Bold.eot
weasy_pdf/static/weasy_pdf/fonts/HelveticaNeueCyr/HelveticaNeueCyr-Bold.ttf
weasy_pdf/static/weasy_pdf/fonts/HelveticaNeueCyr/HelveticaNeueCyr-Bold.woff
weasy_pdf/static/weasy_pdf/fonts/HelveticaNeueCyr/HelveticaNeueCyr-BoldItalic.eot
weasy_pdf/static/weasy_pdf/fonts/HelveticaNeueCyr/HelveticaNeueCyr-BoldItalic.ttf
weasy_pdf/static/weasy_pdf/fonts/HelveticaNeueCyr/HelveticaNeueCyr-BoldItalic.woff
weasy_pdf/static/weasy_pdf/fonts/HelveticaNeueCyr/HelveticaNeueCyr-Heavy.eot
weasy_pdf/static/weasy_pdf/fonts/HelveticaNeueCyr/HelveticaNeueCyr-Heavy.ttf
weasy_pdf/static/weasy_pdf/fonts/HelveticaNeueCyr/HelveticaNeueCyr-Heavy.woff
weasy_pdf/static/weasy_pdf/fonts/HelveticaNeueCyr/HelveticaNeueCyr-HeavyItalic.eot
weasy_pdf/static/weasy_pdf/fonts/HelveticaNeueCyr/HelveticaNeueCyr-HeavyItalic.ttf
weasy_pdf/static/weasy_pdf/fonts/HelveticaNeueCyr/HelveticaNeueCyr-HeavyItalic.woff
weasy_pdf/static/weasy_pdf/fonts/HelveticaNeueCyr/HelveticaNeueCyr-Italic.eot
weasy_pdf/static/weasy_pdf/fonts/HelveticaNeueCyr/HelveticaNeueCyr-Italic.ttf
weasy_pdf/static/weasy_pdf/fonts/HelveticaNeueCyr/HelveticaNeueCyr-Italic.woff
weasy_pdf/static/weasy_pdf/fonts/HelveticaNeueCyr/HelveticaNeueCyr-Light.eot
