Metadata-Version: 1.1
Name: btc-weasy-pdf
Version: 0.3
Summary: View mixin and template filters for PDF creation from the HTML-template.
Home-page: https://github.com/MEADez/btc-weasy-pdf
Author: MEADez
Author-email: m3adez@gmail.com
License: BSD License
Platform: UNKNOWN
Classifier: Environment :: Web Environment
Classifier: Framework :: Django
Classifier: Intended Audience :: Developers
Classifier: License :: OSI Approved :: BSD License
Classifier: Operating System :: OS Independent
Classifier: Programming Language :: Python :: 3.7
Classifier: Topic :: Internet :: WWW/HTTP
Classifier: Topic :: Internet :: WWW/HTTP :: Dynamic Content
